metaclean3/__init__.py
metaclean3/binning.py
metaclean3/changepoint.py
metaclean3/channels.py
metaclean3/fcs.py
metaclean3/features.py
metaclean3/metaclean.py
metaclean3/outliers.py
metaclean3/plot.py
metaclean3/segments.py
metaclean3/utils.py
metaclean3-0.1.1.dist-info/WHEEL
metaclean3-0.1.1.dist-info/METADATA
metaclean3-0.1.1.dist-info/RECORD
