Metadata-Version: 2.1
Name: metaclean3
Version: 0.1.1
Summary: Removes anomalous events from flow cytometry standard (FCS) files.
Author-email: Alice Yue <alice.ky@live.ca>
Requires-Python: >=3.10.0
Classifier: License :: OSI Approved :: MIT License
Classifier: Programming Language :: Python :: 3 :: Only
Requires-Dist: kneed >= 0.8.5
Requires-Dist: matplotlib >= 3.5.1
Requires-Dist: numpy >= 1.20.0
Requires-Dist: pandas >= 2.0.2
Requires-Dist: ruptures >= 1.1.7
Requires-Dist: scikit-learn >= 1.2.2
Requires-Dist: scipy >= 1.10.0
Requires-Dist: build ; extra == "dev"
Requires-Dist: ddt ; extra == "dev"
Requires-Dist: fcsparser ; extra == "dev"
Requires-Dist: pip-tools ; extra == "dev"
Requires-Dist: pytest ; extra == "dev"
Requires-Dist: Sphinx >= 5.1.1 ; extra == "dev"
Requires-Dist: twine ; extra == "dev"
Project-URL: Documentation, https://metafora-biosystems.gitlab.io/-/data-science-dev/metaclean3_public/-/jobs/5719586985/artifacts/public/autoapi/metaclean3/index.html
Project-URL: Source, https://gitlab.com/metafora-biosystems_public/metaclean3
Project-URL: Tracker, https://gitlab.com/metafora-biosystems_public/metaclean3/-/issues
Provides-Extra: dev
